items/__init__.py
items/core.py
items-0.6.5.dist-info/LICENSE.txt
items-0.6.5.dist-info/METADATA
items-0.6.5.dist-info/WHEEL
items-0.6.5.dist-info/top_level.txt
items-0.6.5.dist-info/RECORD
